toolip/__init__.py
toolip/fastapi/__init__.py
toolip/fastapi/app.py
toolip/fastapi/config.py
toolip/fastapi/constants.py
toolip/utils/__init__.py
toolip/utils/config.py
toolip/utils/logs.py
toolip/utils/misc.py
toolip/utils/redoc.py
toolip/utils/time.py
toolip-0.2.dist-info/LICENSE
toolip-0.2.dist-info/WHEEL
toolip-0.2.dist-info/METADATA
toolip-0.2.dist-info/RECORD
