Metadata-Version: 2.1
Name: toolip
Version: 0.2
Summary: A collection of python utils for webapps.
Home-page: https://github.com/SatelCreative/toolip
Author: Anthony Hillairet
Author-email: ant@satel.ca
Classifier: License :: OSI Approved :: MIT License
